freeGPTFix/Exceptions.py
freeGPTFix/__init__.py
freeGPTFix/Client/__init__.py
freeGPTFix/Client/gemini.py
freeGPTFix/Client/gpt3.py
freeGPTFix/Client/gpt3_5.py
freeGPTFix/Client/gpt4.py
freeGPTFix/Client/gpt4_omni.py
freeGPTFix/Client/pollinations.py
freeGPTFix/Client/prodia.py
freeGPTFix/lib/__init__.py
freeGPTFix/lib/headers.py
freeGPTFix/lib/helper.py
freeGPTFix/lib/models.py
freeGPTFix/lib/proxy.py
freeGPTFix/lib/room.py
freeGPTFix/lib/roles/__init__.py
freeGPTFix/lib/roles/character_loader.py
freeGPTFix/lib/roles/roles.py
freeGPTFix/lib/roles/Characters/__init__.py
freeGPTFix/lib/roles/Characters/Hunter_X_Hunter/__init__.py
freeGPTFix/lib/roles/Characters/Hunter_X_Hunter/gon.py
freeGPTFix/lib/roles/Characters/Hunter_X_Hunter/killua.py
freeGPTFix/lib/roles/Characters/Hunter_X_Hunter/meruem.py
freeGPTFix/lib/roles/Characters/Hunter_X_Hunter/netero.py
freeGPTFix/lib/roles/Characters/KimetsuNoYaiba/__init__.py
freeGPTFix/lib/roles/Characters/KimetsuNoYaiba/rengoku.py
freeGPTFix/lib/roles/Characters/Other/__init__.py
freeGPTFix/lib/roles/Characters/Other/friend.py
freeGPTFix/lib/roles/Characters/Other/historian.py
freeGPTFix/lib/roles/Characters/Other/psychiatrist.py
freeGPTFix/lib/roles/Characters/Undertale/__init__.py
freeGPTFix/lib/roles/Characters/Undertale/alphis.py
freeGPTFix/lib/roles/Characters/Undertale/gaster.py
freeGPTFix/lib/roles/Characters/Undertale/papyrus.py
freeGPTFix/lib/roles/Characters/Undertale/sans.py
freeGPTFix-1.3.0.dist-info/LICENSE
freeGPTFix-1.3.0.dist-info/METADATA
freeGPTFix-1.3.0.dist-info/WHEEL
freeGPTFix-1.3.0.dist-info/top_level.txt
freeGPTFix-1.3.0.dist-info/RECORD
