Metadata-Version: 2.1
Name: freeGPTFix
Version: 1.3.0
Summary: freeGPT provides free access to text and image generation models.
Home-page: https://github.com/RedPiarOfficial/FreeGPTFix
Author: RedPiar
Author-email: Redpiar.official@gmail.com
License: MIT
Project-URL: Source, https://github.com/RedPiarOfficial/FreeGPTFix
Keywords: artificial-intelligence,machine-learning,deep-learning,gpt4free,gpt4all,freegpt,chatgpt,python,llama,llm,nlp,gpt,ai
Classifier: Programming Language :: Python :: 3
Classifier: License :: OSI Approved :: MIT License
Classifier: Operating System :: OS Independent
Requires-Python: >=3.8
License-File: LICENSE
Requires-Dist: requests
